nis2pyr/__init__.py
nis2pyr/__main__.py
nis2pyr/convertor.py
nis2pyr/metadata.py
nis2pyr/nis2pyr.py
nis2pyr/reader.py
nis2pyr/writer.py
nis2pyr-0.6.2.dist-info/LICENSE
nis2pyr-0.6.2.dist-info/METADATA
nis2pyr-0.6.2.dist-info/WHEEL
nis2pyr-0.6.2.dist-info/entry_points.txt
nis2pyr-0.6.2.dist-info/top_level.txt
nis2pyr-0.6.2.dist-info/RECORD
