Metadata-Version: 2.1
Name: nis2pyr
Version: 0.6.2
Summary: Utility for converting Nikon ND2 files to tiled pyramidal OME TIFF files.
Home-page: https://github.com/vibbits/nis2pyr
Author: Frank Vernaillen
Author-email: frank.vernaillen@vib.be
License: BSD-3-Clause
Project-URL: Bug Tracker, https://github.com/vibbits/nis2pyr/issues
Classifier: Development Status :: 3 - Alpha
Classifier: License :: OSI Approved :: BSD License
Classifier: Programming Language :: Python :: 3
Classifier: Programming Language :: Python :: 3 :: Only
Classifier: Programming Language :: Python :: 3.7
Classifier: Programming Language :: Python :: 3.8
Classifier: Programming Language :: Python :: 3.9
Classifier: Topic :: Scientific/Engineering
Classifier: Natural Language :: English
Requires-Python: <3.10,>=3.7
License-File: LICENSE
Requires-Dist: tifffile (==2021.8.30)
Requires-Dist: imagecodecs (==2021.8.26)
Requires-Dist: opencv-python (==4.5.3.56)
Requires-Dist: ome-types (==0.2.9)
Requires-Dist: nd2 (==0.1.4)
Requires-Dist: importlib-metadata (==4.8.1) ; python_version < "3.8"
Provides-Extra: dev
Requires-Dist: coverage ; extra == 'dev'
Requires-Dist: flake8 ; extra == 'dev'
Requires-Dist: mypy ; extra == 'dev'
Requires-Dist: pyinstaller ; extra == 'dev'
Requires-Dist: pytest ; extra == 'dev'
Requires-Dist: pytest-cov ; extra == 'dev'
Requires-Dist: pytest-mock ; extra == 'dev'
